{
    "__meta__": {
        "version": [
            2,
            5
        ],
        "compiler": "https://github.com/p4lang/p4c-bm"
    },
    "header_types": [
        {
            "name": "standard_metadata_t",
            "id": 0,
            "fields": [
                [
                    "ingress_port",
                    9
                ],
                [
                    "packet_length",
                    32
                ],
                [
                    "egress_spec",
                    9
                ],
                [
                    "egress_port",
                    9
                ],
                [
                    "egress_instance",
                    32
                ],
                [
                    "instance_type",
                    32
                ],
                [
                    "clone_spec",
                    32
                ],
                [
                    "_padding",
                    5
                ]
            ],
            "length_exp": null,
            "max_length": null
        },
        {
            "name": "ethernet_t",
            "id": 1,
            "fields": [
                [
                    "dstAddr",
                    48
                ],
                [
                    "srcAddr",
                    48
                ],
                [
                    "etherType",
                    16
                ]
            ],
            "length_exp": null,
            "max_length": null
        },
        {
            "name": "ipv4_t",
            "id": 2,
            "fields": [
                [
                    "version",
                    4
                ],
                [
                    "ihl",
                    4
                ],
                [
                    "diffserv",
                    8
                ],
                [
                    "totalLen",
                    16
                ],
                [
                    "identification",
                    16
                ],
                [
                    "flags",
                    3
                ],
                [
                    "fragOffset",
                    13
                ],
                [
                    "ttl",
                    8
                ],
                [
                    "protocol",
                    8
                ],
                [
                    "hdrChecksum",
                    16
                ],
                [
                    "srcAddr",
                    32
                ],
                [
                    "dstAddr",
                    32
                ]
            ],
            "length_exp": null,
            "max_length": null
        },
        {
            "name": "tcp_t",
            "id": 3,
            "fields": [
                [
                    "srcPort",
                    16
                ],
                [
                    "dstPort",
                    16
                ],
                [
                    "seqNo",
                    32
                ],
                [
                    "ackNo",
                    32
                ],
                [
                    "dataOffset",
                    4
                ],
                [
                    "res",
                    4
                ],
                [
                    "flags",
                    8
                ],
                [
                    "window",
                    16
                ],
                [
                    "checksum",
                    16
                ],
                [
                    "urgentPtr",
                    16
                ]
            ],
            "length_exp": null,
            "max_length": null
        },
        {
            "name": "udp_t",
            "id": 4,
            "fields": [
                [
                    "srcPort",
                    16
                ],
                [
                    "dstPort",
                    16
                ],
                [
                    "length_",
                    16
                ],
                [
                    "checksum",
                    16
                ]
            ],
            "length_exp": null,
            "max_length": null
        },
        {
            "name": "meta_t",
            "id": 5,
            "fields": [
                [
                    "tcpLength",
                    16
                ],
                [
                    "natReverse",
                    1
                ],
                [
                    "natForward",
                    1
                ],
                [
                    "_padding",
                    6
                ]
            ],
            "length_exp": null,
            "max_length": null
        },
        {
            "name": "l3_metadata_t",
            "id": 6,
            "fields": [
                [
                    "lkp_ip_type",
                    2
                ],
                [
                    "lkp_ip_version",
                    4
                ],
                [
                    "lkp_ip_proto",
                    8
                ],
                [
                    "lkp_dscp",
                    8
                ],
                [
                    "lkp_ip_ttl",
                    8
                ],
                [
                    "lkp_l4_sport",
                    16
                ],
                [
                    "lkp_l4_dport",
                    16
                ],
                [
                    "lkp_outer_l4_sport",
                    16
                ],
                [
                    "lkp_outer_l4_dport",
                    16
                ],
                [
                    "vrf",
                    16
                ],
                [
                    "rmac_group",
                    10
                ],
                [
                    "rmac_hit",
                    1
                ],
                [
                    "urpf_mode",
                    2
                ],
                [
                    "urpf_hit",
                    1
                ],
                [
                    "urpf_check_fail",
                    1
                ],
                [
                    "urpf_bd_group",
                    16
                ],
                [
                    "fib_hit",
                    1
                ],
                [
                    "fib_nexthop",
                    16
                ],
                [
                    "fib_nexthop_type",
                    2
                ],
                [
                    "same_bd_check",
                    16
                ],
                [
                    "nexthop_index",
                    16
                ],
                [
                    "routed",
                    1
                ],
                [
                    "outer_routed",
                    1
                ],
                [
                    "mtu_index",
                    8
                ],
                [
                    "l3_copy",
                    1
                ],
                [
                    "l3_mtu_check",
                    16,
                    false,
                    true
                ],
                [
                    "egress_l4_sport",
                    16
                ],
                [
                    "egress_l4_dport",
                    16
                ],
                [
                    "_padding",
                    5
                ]
            ],
            "length_exp": null,
            "max_length": null
        },
        {
            "name": "routing_metadata_t",
            "id": 7,
            "fields": [
                [
                    "nhop_ipv4",
                    32
                ]
            ],
            "length_exp": null,
            "max_length": null
        }
    ],
    "headers": [
        {
            "name": "standard_metadata",
            "id": 0,
            "header_type": "standard_metadata_t",
            "metadata": true
        },
        {
            "name": "ethernet",
            "id": 1,
            "header_type": "ethernet_t",
            "metadata": false
        },
        {
            "name": "ipv4",
            "id": 2,
            "header_type": "ipv4_t",
            "metadata": false
        },
        {
            "name": "tcp",
            "id": 3,
            "header_type": "tcp_t",
            "metadata": false
        },
        {
            "name": "udp",
            "id": 4,
            "header_type": "udp_t",
            "metadata": false
        },
        {
            "name": "meta",
            "id": 5,
            "header_type": "meta_t",
            "metadata": true
        },
        {
            "name": "l3_metadata",
            "id": 6,
            "header_type": "l3_metadata_t",
            "metadata": true
        },
        {
            "name": "routing_metadata",
            "id": 7,
            "header_type": "routing_metadata_t",
            "metadata": true
        }
    ],
    "header_stacks": [],
    "parsers": [
        {
            "name": "parser",
            "id": 0,
            "init_state": "start",
            "parse_states": [
                {
                    "name": "start",
                    "id": 0,
                    "parser_ops": [],
                    "transition_key": [],
                    "transitions": [
                        {
                            "type": "default",
                            "value": null,
                            "mask": null,
                            "next_state": "parse_ethernet"
                        }
                    ]
                },
                {
                    "name": "parse_ethernet",
                    "id": 1,
                    "parser_ops": [
                        {
                            "op": "extract",
                            "parameters": [
                                {
                                    "type": "regular",
                                    "value": "ethernet"
                                }
                            ]
                        }
                    ],
                    "transition_key": [
                        {
                            "type": "field",
                            "value": [
                                "ethernet",
                                "etherType"
                            ]
                        }
                    ],
                    "transitions": [
                        {
                            "type": "hexstr",
                            "value": "0x0800",
                            "mask": null,
                            "next_state": "parse_ipv4"
                        },
                        {
                            "type": "default",
                            "value": null,
                            "mask": null,
                            "next_state": null
                        }
                    ]
                },
                {
                    "name": "parse_ipv4",
                    "id": 2,
                    "parser_ops": [
                        {
                            "op": "extract",
                            "parameters": [
                                {
                                    "type": "regular",
                                    "value": "ipv4"
                                }
                            ]
                        },
                        {
                            "op": "set",
                            "parameters": [
                                {
                                    "type": "field",
                                    "value": [
                                        "meta",
                                        "tcpLength"
                                    ]
                                },
                                {
                                    "type": "expression",
                                    "value": {
                                        "type": "expression",
                                        "value": {
                                            "op": "-",
                                            "left": {
                                                "type": "field",
                                                "value": [
                                                    "ipv4",
                                                    "totalLen"
                                                ]
                                            },
                                            "right": {
                                                "type": "hexstr",
                                                "value": "0x14"
                                            }
                                        }
                                    }
                                }
                            ]
                        }
                    ],
                    "transition_key": [
                        {
                            "type": "field",
                            "value": [
                                "ipv4",
                                "fragOffset"
                            ]
                        },
                        {
                            "type": "field",
                            "value": [
                                "ipv4",
                                "ihl"
                            ]
                        },
                        {
                            "type": "field",
                            "value": [
                                "ipv4",
                                "protocol"
                            ]
                        }
                    ],
                    "transitions": [
                        {
                            "type": "hexstr",
                            "value": "0x00000506",
                            "mask": null,
                            "next_state": "parse_tcp"
                        },
                        {
                            "type": "hexstr",
                            "value": "0x00000511",
                            "mask": null,
                            "next_state": "parse_udp"
                        },
                        {
                            "type": "default",
                            "value": null,
                            "mask": null,
                            "next_state": null
                        }
                    ]
                },
                {
                    "name": "parse_tcp",
                    "id": 3,
                    "parser_ops": [
                        {
                            "op": "extract",
                            "parameters": [
                                {
                                    "type": "regular",
                                    "value": "tcp"
                                }
                            ]
                        },
                        {
                            "op": "set",
                            "parameters": [
                                {
                                    "type": "field",
                                    "value": [
                                        "l3_metadata",
                                        "lkp_outer_l4_sport"
                                    ]
                                },
                                {
                                    "type": "field",
                                    "value": [
                                        "tcp",
                                        "srcPort"
                                    ]
                                }
                            ]
                        },
                        {
                            "op": "set",
                            "parameters": [
                                {
                                    "type": "field",
                                    "value": [
                                        "l3_metadata",
                                        "lkp_outer_l4_dport"
                                    ]
                                },
                                {
                                    "type": "field",
                                    "value": [
                                        "tcp",
                                        "dstPort"
                                    ]
                                }
                            ]
                        }
                    ],
                    "transition_key": [],
                    "transitions": [
                        {
                            "type": "default",
                            "value": null,
                            "mask": null,
                            "next_state": null
                        }
                    ]
                },
                {
                    "name": "parse_udp",
                    "id": 4,
                    "parser_ops": [
                        {
                            "op": "extract",
                            "parameters": [
                                {
                                    "type": "regular",
                                    "value": "udp"
                                }
                            ]
                        },
                        {
                            "op": "set",
                            "parameters": [
                                {
                                    "type": "field",
                                    "value": [
                                        "l3_metadata",
                                        "lkp_outer_l4_sport"
                                    ]
                                },
                                {
                                    "type": "field",
                                    "value": [
                                        "udp",
                                        "srcPort"
                                    ]
                                }
                            ]
                        },
                        {
                            "op": "set",
                            "parameters": [
                                {
                                    "type": "field",
                                    "value": [
                                        "l3_metadata",
                                        "lkp_outer_l4_dport"
                                    ]
                                },
                                {
                                    "type": "field",
                                    "value": [
                                        "udp",
                                        "dstPort"
                                    ]
                                }
                            ]
                        }
                    ],
                    "transition_key": [],
                    "transitions": [
                        {
                            "type": "default",
                            "value": null,
                            "mask": null,
                            "next_state": null
                        }
                    ]
                }
            ]
        }
    ],
    "parse_vsets": [],
    "deparsers": [
        {
            "name": "deparser",
            "id": 0,
            "order": [
                "ethernet",
                "ipv4",
                "udp",
                "tcp"
            ]
        }
    ],
    "meter_arrays": [],
    "actions": [
        {
            "name": "set_nhop",
            "id": 0,
            "runtime_data": [
                {
                    "name": "nhop_ipv4",
                    "bitwidth": 32
                },
                {
                    "name": "port",
                    "bitwidth": 9
                }
            ],
            "primitives": [
                {
                    "op": "modify_field",
                    "parameters": [
                        {
                            "type": "field",
                            "value": [
                                "routing_metadata",
                                "nhop_ipv4"
                            ]
                        },
                        {
                            "type": "runtime_data",
                            "value": 0
                        }
                    ]
                },
                {
                    "op": "modify_field",
                    "parameters": [
                        {
                            "type": "field",
                            "value": [
                                "standard_metadata",
                                "egress_spec"
                            ]
                        },
                        {
                            "type": "runtime_data",
                            "value": 1
                        }
                    ]
                },
                {
                    "op": "add_to_field",
                    "parameters": [
                        {
                            "type": "field",
                            "value": [
                                "ipv4",
                                "ttl"
                            ]
                        },
                        {
                            "type": "hexstr",
                            "value": "-0x1"
                        }
                    ]
                }
            ]
        },
        {
            "name": "rewrite_dstAddrTCP",
            "id": 1,
            "runtime_data": [
                {
                    "name": "ipv4Addr",
                    "bitwidth": 32
                },
                {
                    "name": "tcpPort",
                    "bitwidth": 16
                }
            ],
            "primitives": [
                {
                    "op": "modify_field",
                    "parameters": [
                        {
                            "type": "field",
                            "value": [
                                "ipv4",
                                "dstAddr"
                            ]
                        },
                        {
                            "type": "runtime_data",
                            "value": 0
                        }
                    ]
                },
                {
                    "op": "modify_field",
                    "parameters": [
                        {
                            "type": "field",
                            "value": [
                                "tcp",
                                "dstPort"
                            ]
                        },
                        {
                            "type": "runtime_data",
                            "value": 1
                        }
                    ]
                },
                {
                    "op": "modify_field",
                    "parameters": [
                        {
                            "type": "field",
                            "value": [
                                "meta",
                                "natReverse"
                            ]
                        },
                        {
                            "type": "hexstr",
                            "value": "0x1"
                        }
                    ]
                }
            ]
        },
        {
            "name": "rewrite_srcAddrTCP",
            "id": 2,
            "runtime_data": [
                {
                    "name": "ipv4Addr",
                    "bitwidth": 32
                },
                {
                    "name": "port",
                    "bitwidth": 16
                }
            ],
            "primitives": [
                {
                    "op": "modify_field",
                    "parameters": [
                        {
                            "type": "field",
                            "value": [
                                "ipv4",
                                "srcAddr"
                            ]
                        },
                        {
                            "type": "runtime_data",
                            "value": 0
                        }
                    ]
                },
                {
                    "op": "modify_field",
                    "parameters": [
                        {
                            "type": "field",
                            "value": [
                                "tcp",
                                "srcPort"
                            ]
                        },
                        {
                            "type": "runtime_data",
                            "value": 1
                        }
                    ]
                },
                {
                    "op": "modify_field",
                    "parameters": [
                        {
                            "type": "field",
                            "value": [
                                "meta",
                                "natForward"
                            ]
                        },
                        {
                            "type": "hexstr",
                            "value": "0x1"
                        }
                    ]
                }
            ]
        },
        {
            "name": "set_dmac",
            "id": 3,
            "runtime_data": [
                {
                    "name": "dmac",
                    "bitwidth": 48
                }
            ],
            "primitives": [
                {
                    "op": "modify_field",
                    "parameters": [
                        {
                            "type": "field",
                            "value": [
                                "ethernet",
                                "dstAddr"
                            ]
                        },
                        {
                            "type": "runtime_data",
                            "value": 0
                        }
                    ]
                }
            ]
        },
        {
            "name": "send_to_cpu",
            "id": 4,
            "runtime_data": [],
            "primitives": [
                {
                    "op": "modify_field",
                    "parameters": [
                        {
                            "type": "field",
                            "value": [
                                "ethernet",
                                "dstAddr"
                            ]
                        },
                        {
                            "type": "hexstr",
                            "value": "0x400000000"
                        }
                    ]
                },
                {
                    "op": "modify_field",
                    "parameters": [
                        {
                            "type": "field",
                            "value": [
                                "routing_metadata",
                                "nhop_ipv4"
                            ]
                        },
                        {
                            "type": "hexstr",
                            "value": "0xa00000a"
                        }
                    ]
                },
                {
                    "op": "modify_field",
                    "parameters": [
                        {
                            "type": "field",
                            "value": [
                                "standard_metadata",
                                "egress_spec"
                            ]
                        },
                        {
                            "type": "hexstr",
                            "value": "0x1"
                        }
                    ]
                },
                {
                    "op": "add_to_field",
                    "parameters": [
                        {
                            "type": "field",
                            "value": [
                                "ipv4",
                                "ttl"
                            ]
                        },
                        {
                            "type": "hexstr",
                            "value": "-0x1"
                        }
                    ]
                }
            ]
        },
        {
            "name": "_drop",
            "id": 5,
            "runtime_data": [],
            "primitives": [
                {
                    "op": "drop",
                    "parameters": []
                }
            ]
        },
        {
            "name": "reg",
            "id": 6,
            "runtime_data": [],
            "primitives": [
                {
                    "op": "modify_field",
                    "parameters": [
                        {
                            "type": "field",
                            "value": [
                                "standard_metadata",
                                "egress_spec"
                            ]
                        },
                        {
                            "type": "hexstr",
                            "value": "0x1"
                        }
                    ]
                }
            ]
        },
        {
            "name": "rewrite_mac",
            "id": 7,
            "runtime_data": [
                {
                    "name": "smac",
                    "bitwidth": 48
                }
            ],
            "primitives": [
                {
                    "op": "modify_field",
                    "parameters": [
                        {
                            "type": "field",
                            "value": [
                                "ethernet",
                                "srcAddr"
                            ]
                        },
                        {
                            "type": "runtime_data",
                            "value": 0
                        }
                    ]
                }
            ]
        }
    ],
    "pipelines": [
        {
            "name": "ingress",
            "id": 0,
            "init_table": "_condition_0",
            "tables": [
                {
                    "name": "ipv4_lpm",
                    "id": 0,
                    "match_type": "lpm",
                    "type": "simple",
                    "max_size": 1024,
                    "with_counters": false,
                    "direct_meters": null,
                    "support_timeout": false,
                    "key": [
                        {
                            "match_type": "lpm",
                            "target": [
                                "ipv4",
                                "dstAddr"
                            ],
                            "mask": null
                        }
                    ],
                    "actions": [
                        "set_nhop",
                        "_drop"
                    ],
                    "next_tables": {
                        "set_nhop": "forward",
                        "_drop": "forward"
                    },
                    "base_default_next": "forward"
                },
                {
                    "name": "forward",
                    "id": 1,
                    "match_type": "exact",
                    "type": "simple",
                    "max_size": 512,
                    "with_counters": false,
                    "direct_meters": null,
                    "support_timeout": false,
                    "key": [
                        {
                            "match_type": "exact",
                            "target": [
                                "routing_metadata",
                                "nhop_ipv4"
                            ],
                            "mask": null
                        }
                    ],
                    "actions": [
                        "set_dmac",
                        "_drop"
                    ],
                    "next_tables": {
                        "set_dmac": null,
                        "_drop": null
                    },
                    "base_default_next": null
                },
                {
                    "name": "rev_nat_tcp",
                    "id": 2,
                    "match_type": "exact",
                    "type": "simple",
                    "max_size": 32768,
                    "with_counters": false,
                    "direct_meters": null,
                    "support_timeout": false,
                    "key": [
                        {
                            "match_type": "exact",
                            "target": [
                                "ipv4",
                                "dstAddr"
                            ],
                            "mask": null
                        },
                        {
                            "match_type": "exact",
                            "target": [
                                "tcp",
                                "dstPort"
                            ],
                            "mask": null
                        }
                    ],
                    "actions": [
                        "rewrite_dstAddrTCP",
                        "_drop"
                    ],
                    "next_tables": {
                        "rewrite_dstAddrTCP": "ipv4_lpm",
                        "_drop": "ipv4_lpm"
                    },
                    "base_default_next": "ipv4_lpm"
                },
                {
                    "name": "match_nat_ip",
                    "id": 3,
                    "match_type": "lpm",
                    "type": "simple",
                    "max_size": 16384,
                    "with_counters": false,
                    "direct_meters": null,
                    "support_timeout": false,
                    "key": [
                        {
                            "match_type": "lpm",
                            "target": [
                                "ipv4",
                                "dstAddr"
                            ],
                            "mask": null
                        }
                    ],
                    "actions": [
                        "reg"
                    ],
                    "next_tables": {
                        "__HIT__": "rev_nat_tcp",
                        "__MISS__": "ipv4_lpm"
                    },
                    "base_default_next": "ipv4_lpm"
                }
            ],
            "action_profiles": [],
            "conditionals": [
                {
                    "name": "_condition_0",
                    "id": 0,
                    "expression": {
                        "type": "expression",
                        "value": {
                            "op": "and",
                            "left": {
                                "type": "expression",
                                "value": {
                                    "op": "valid",
                                    "left": null,
                                    "right": {
                                        "type": "header",
                                        "value": "ipv4"
                                    }
                                }
                            },
                            "right": {
                                "type": "expression",
                                "value": {
                                    "op": ">",
                                    "left": {
                                        "type": "field",
                                        "value": [
                                            "ipv4",
                                            "ttl"
                                        ]
                                    },
                                    "right": {
                                        "type": "hexstr",
                                        "value": "0x0"
                                    }
                                }
                            }
                        }
                    },
                    "true_next": "_condition_1",
                    "false_next": null
                },
                {
                    "name": "_condition_1",
                    "id": 1,
                    "expression": {
                        "type": "expression",
                        "value": {
                            "op": "valid",
                            "left": null,
                            "right": {
                                "type": "header",
                                "value": "tcp"
                            }
                        }
                    },
                    "true_next": "match_nat_ip",
                    "false_next": "ipv4_lpm"
                }
            ]
        },
        {
            "name": "egress",
            "id": 1,
            "init_table": "_condition_2",
            "tables": [
                {
                    "name": "send_frame",
                    "id": 4,
                    "match_type": "exact",
                    "type": "simple",
                    "max_size": 256,
                    "with_counters": false,
                    "direct_meters": null,
                    "support_timeout": false,
                    "key": [
                        {
                            "match_type": "exact",
                            "target": [
                                "standard_metadata",
                                "egress_port"
                            ],
                            "mask": null
                        }
                    ],
                    "actions": [
                        "rewrite_mac",
                        "_drop"
                    ],
                    "next_tables": {
                        "rewrite_mac": null,
                        "_drop": null
                    },
                    "base_default_next": null
                },
                {
                    "name": "fwd_nat_tcp",
                    "id": 5,
                    "match_type": "exact",
                    "type": "simple",
                    "max_size": 32768,
                    "with_counters": false,
                    "direct_meters": null,
                    "support_timeout": false,
                    "key": [
                        {
                            "match_type": "exact",
                            "target": [
                                "ipv4",
                                "srcAddr"
                            ],
                            "mask": null
                        },
                        {
                            "match_type": "exact",
                            "target": [
                                "tcp",
                                "srcPort"
                            ],
                            "mask": null
                        }
                    ],
                    "actions": [
                        "rewrite_srcAddrTCP",
                        "send_to_cpu"
                    ],
                    "next_tables": {
                        "rewrite_srcAddrTCP": "send_frame",
                        "send_to_cpu": "send_frame"
                    },
                    "base_default_next": "send_frame"
                }
            ],
            "action_profiles": [],
            "conditionals": [
                {
                    "name": "_condition_2",
                    "id": 2,
                    "expression": {
                        "type": "expression",
                        "value": {
                            "op": "and",
                            "left": {
                                "type": "expression",
                                "value": {
                                    "op": "valid",
                                    "left": null,
                                    "right": {
                                        "type": "header",
                                        "value": "tcp"
                                    }
                                }
                            },
                            "right": {
                                "type": "expression",
                                "value": {
                                    "op": "==",
                                    "left": {
                                        "type": "field",
                                        "value": [
                                            "meta",
                                            "natForward"
                                        ]
                                    },
                                    "right": {
                                        "type": "hexstr",
                                        "value": "0x0"
                                    }
                                }
                            }
                        }
                    },
                    "true_next": "fwd_nat_tcp",
                    "false_next": "send_frame"
                }
            ]
        }
    ],
    "calculations": [
        {
            "name": "ipv4_checksum",
            "id": 0,
            "input": [
                {
                    "type": "field",
                    "value": [
                        "ipv4",
                        "version"
                    ]
                },
                {
                    "type": "field",
                    "value": [
                        "ipv4",
                        "ihl"
                    ]
                },
                {
                    "type": "field",
                    "value": [
                        "ipv4",
                        "diffserv"
                    ]
                },
                {
                    "type": "field",
                    "value": [
                        "ipv4",
                        "totalLen"
                    ]
                },
                {
                    "type": "field",
                    "value": [
                        "ipv4",
                        "identification"
                    ]
                },
                {
                    "type": "field",
                    "value": [
                        "ipv4",
                        "flags"
                    ]
                },
                {
                    "type": "field",
                    "value": [
                        "ipv4",
                        "fragOffset"
                    ]
                },
                {
                    "type": "field",
                    "value": [
                        "ipv4",
                        "ttl"
                    ]
                },
                {
                    "type": "field",
                    "value": [
                        "ipv4",
                        "protocol"
                    ]
                },
                {
                    "type": "field",
                    "value": [
                        "ipv4",
                        "srcAddr"
                    ]
                },
                {
                    "type": "field",
                    "value": [
                        "ipv4",
                        "dstAddr"
                    ]
                }
            ],
            "algo": "csum16"
        },
        {
            "name": "tcp_checksum",
            "id": 1,
            "input": [
                {
                    "type": "field",
                    "value": [
                        "ipv4",
                        "srcAddr"
                    ]
                },
                {
                    "type": "field",
                    "value": [
                        "ipv4",
                        "dstAddr"
                    ]
                },
                {
                    "type": "hexstr",
                    "value": "0x00",
                    "bitwidth": 8
                },
                {
                    "type": "field",
                    "value": [
                        "ipv4",
                        "protocol"
                    ]
                },
                {
                    "type": "field",
                    "value": [
                        "meta",
                        "tcpLength"
                    ]
                },
                {
                    "type": "field",
                    "value": [
                        "tcp",
                        "srcPort"
                    ]
                },
                {
                    "type": "field",
                    "value": [
                        "tcp",
                        "dstPort"
                    ]
                },
                {
                    "type": "field",
                    "value": [
                        "tcp",
                        "seqNo"
                    ]
                },
                {
                    "type": "field",
                    "value": [
                        "tcp",
                        "ackNo"
                    ]
                },
                {
                    "type": "field",
                    "value": [
                        "tcp",
                        "dataOffset"
                    ]
                },
                {
                    "type": "field",
                    "value": [
                        "tcp",
                        "res"
                    ]
                },
                {
                    "type": "field",
                    "value": [
                        "tcp",
                        "flags"
                    ]
                },
                {
                    "type": "field",
                    "value": [
                        "tcp",
                        "window"
                    ]
                },
                {
                    "type": "field",
                    "value": [
                        "tcp",
                        "urgentPtr"
                    ]
                },
                {
                    "type": "header",
                    "value": "udp"
                },
                {
                    "type": "payload"
                }
            ],
            "algo": "csum16"
        }
    ],
    "checksums": [
        {
            "name": "ipv4.hdrChecksum|ipv4_checksum",
            "id": 0,
            "target": [
                "ipv4",
                "hdrChecksum"
            ],
            "type": "generic",
            "calculation": "ipv4_checksum",
            "if_cond": {
                "type": "expression",
                "value": {
                    "op": "==",
                    "left": {
                        "type": "field",
                        "value": [
                            "ipv4",
                            "ihl"
                        ]
                    },
                    "right": {
                        "type": "hexstr",
                        "value": "0x5"
                    }
                }
            }
        },
        {
            "name": "tcp.checksum|tcp_checksum",
            "id": 1,
            "target": [
                "tcp",
                "checksum"
            ],
            "type": "generic",
            "calculation": "tcp_checksum",
            "if_cond": {
                "type": "expression",
                "value": {
                    "op": "valid",
                    "left": null,
                    "right": {
                        "type": "header",
                        "value": "tcp"
                    }
                }
            }
        }
    ],
    "learn_lists": [],
    "field_lists": [],
    "counter_arrays": [],
    "register_arrays": [],
    "force_arith": [
        [
            "standard_metadata",
            "ingress_port"
        ],
        [
            "standard_metadata",
            "packet_length"
        ],
        [
            "standard_metadata",
            "egress_spec"
        ],
        [
            "standard_metadata",
            "egress_port"
        ],
        [
            "standard_metadata",
            "egress_instance"
        ],
        [
            "standard_metadata",
            "instance_type"
        ],
        [
            "standard_metadata",
            "clone_spec"
        ],
        [
            "standard_metadata",
            "_padding"
        ]
    ]
}